ansys/api/mechanical/VERSION
ansys/api/mechanical/__init__.py
ansys/api/mechanical/py.typed
ansys/api/mechanical/v0/mechanical_pb2.py
ansys/api/mechanical/v0/mechanical_pb2.pyi
ansys/api/mechanical/v0/mechanical_pb2_grpc.py
ansys/api/mechanical/v0/mechanical_pb2_grpc.pyi
ansys_api_mechanical-0.1.3.dist-info/licenses/LICENSE
ansys_api_mechanical-0.1.3.dist-info/METADATA
ansys_api_mechanical-0.1.3.dist-info/WHEEL
ansys_api_mechanical-0.1.3.dist-info/entry_points.txt
ansys_api_mechanical-0.1.3.dist-info/top_level.txt
ansys_api_mechanical-0.1.3.dist-info/RECORD
