Metadata-Version: 2.4
Name: ansys-api-mechanical
Version: 0.1.3
Summary: Autogenerated python gRPC interface package for ansys-api-mechanical, built on 13:28:47 on 04 August 2025
Home-page: https://github.com/ansys/ansys-api-mechanical
Author: ANSYS, Inc.
Author-email: support@ansys.com
License: MIT
Requires-Python: >=3.7
License-File: LICENSE
Requires-Dist: grpcio~=1.30
Requires-Dist: protobuf<6,>=3.19
Dynamic: author
Dynamic: author-email
Dynamic: description
Dynamic: description-content-type
Dynamic: home-page
Dynamic: license
Dynamic: license-file
Dynamic: requires-dist
Dynamic: requires-python
Dynamic: summary
